llm_workers_tools/__init__.py
llm_workers_tools/chat_main.py
llm_workers_tools/cli_main.py
llm_workers_tools-1.0.0.dist-info/METADATA
llm_workers_tools-1.0.0.dist-info/WHEEL
llm_workers_tools-1.0.0.dist-info/entry_points.txt
llm_workers_tools-1.0.0.dist-info/RECORD
