Metadata-Version: 2.3
Name: llm-workers-tools
Version: 1.0.0
Summary: Command-line tools for LLM Workers - llm-workers-cli and llm-workers-chat
Author: Dmitry Mikhaylov
Author-email: mikhailov.dmitry@gmail.com
Requires-Python: >=3.12,<3.15
Classifier: Programming Language :: Python :: 3
Classifier: Programming Language :: Python :: 3.12
Classifier: Programming Language :: Python :: 3.13
Requires-Dist: langchain-anthropic (>=1.0.0,<2.0.0)
Requires-Dist: langchain-google-genai (>=4.0.0,<5.0.0)
Requires-Dist: langchain-openai (>=1.0.0,<2.0.0)
Requires-Dist: llm-workers (==1.0.0)
Requires-Dist: llm-workers-console (==1.0.0)
Project-URL: Homepage, https://mrbagheera.github.io/llm-workers/
Project-URL: Issues, https://github.com/MrBagheera/llm-workers/issues
